battleship/__init__.py
battleship/__main__.py
battleship/board.py
battleship/config.py
battleship/engine.py
battleship/game.py
battleship/players.py
battleship/ship.py
battleship/ui.py
bship-0.1.0.dist-info/LICENSE
bship-0.1.0.dist-info/METADATA
bship-0.1.0.dist-info/WHEEL
bship-0.1.0.dist-info/entry_points.txt
bship-0.1.0.dist-info/top_level.txt
bship-0.1.0.dist-info/RECORD
